Workbook

Sheet README
A1: TITAN MARKETS LLC
A2: TFBS Portfolio Backtest — Results Workbook
A3: Companion to TFBS_Backtest_Report.pdf; same run, same numbers.
A5: THIS IS NOT A PERFORMANCE RECORD. This run used deterministic SYNTHETIC price data — textbook formations followed by completed measured moves. Every performance figure in this workbook is a property of that generated price path, not evidence that the strategy has an edge. Do not present it to clients, prospects, program participants or regulators as a track record. Re-run against firm market data before drawing any conclusion.
A9: Period | B9: 2026-01-05 to 2026-01-19
A10: Instruments | B10: GC, EURUSD, GBPUSD, USDJPY, CL, NQ, ES, RTY
A11: Bars processed | B11: 33,840 (5-minute)
A12: Data source | B12: Deterministic synthetic price paths
A13: Account | B13: TITAN-DESK-01 · $500,000 · prop_desk
A14: Generated | B14: 2026-08-12 06:05:44 UTC
A15: Engine | B15: titan_tfbs v1.0.0
A17: How to read this workbook
A18: Trades | B18: One row per closed trade — the Ch XIII-A journal field set. This is the source of truth; every other sheet computes from it.
A19: Research | B19: Ch XIII-A: why each trade was taken, written by the engine from the objects it decided on — including what was weak about the setup, recorded before the outcome was known.
A20: Summary | B20: Headline metrics, all as live formulas over Trades. Filter or delete rows in Trades and these update.
A21: By Instrument | B21: Per-symbol performance via SUMIFS/COUNTIFS over Trades.
A22: By Pattern | B22: Ch XIII-C review input: which formations paid.
A23: By Grade | B23: Ch XI confluence grade vs outcome — the score-to-outcome check.
A24: Setup Funnel | B24: Why setups were refused. Ch XII-A4 requires the skips to be logged, and they show what the rules actually do.
A25: Risk & Compliance | B25: Peak open risk against the Ch VIII-A cap, and the RMG s.05 account status timeline.
A26: Equity Curve | B26: Sampled equity, with high-water mark and drawdown as formulas.
A27: Config | B27: Every risk parameter the run applied, with its manual citation.
A29: Assumptions
A30: • | B30: Fills simulated with a fixed spread, slippage and commission model; real execution will differ, increasingly so with size.
A31: • | B31: A bar spanning both stop and target is assumed to hit the STOP first — deliberately pessimistic, but an assumption.
A32: • | B32: No economic calendar supplied, so the Ch XII-A6 news blackout was inactive.
A33: • | B33: Instruments were replayed interleaved in timestamp order so the Ch VIII-A portfolio caps bind correctly.
A34: • | B34: Order within a shared timestamp is rotated, not fixed: a fixed order gives the same instrument the last slice of the 5% risk headroom at every contested bar. Per-instrument rows are portfolio contributions, not standalone results.

Sheet Trades
A1: Trade ID | B1: Symbol | C1: Asset class | D1: Direction | E1: Formation | F1: Pattern TF | G1: Method | H1: Grade | I1: Score | J1: Entry time | K1: Exit time | L1: Entry | M1: Stop | N1: TP1 | O1: TP2 | P1: Size | Q1: Risk % | R1: Planned R:R | S1: Realised R | T1: P&L | U1: Result | V1: Max fav R | W1: Max adv R | X1: Bars open | Y1: Exit reason
A2: T00001 | B2: GC | C2: commodities | D2: short | E2: H&S | F2: 1H | G2: B | H2: APPROVED | I2: 7 | J2: 2026-01-09 06:15:00 | K2: 2026-01-09 19:35:00 | L2: 2693.5 | M2: 2695.5419 | N2: 2634.8757 | O2: 2626.8413 | P2: 30 | Q2: 0.012148571 | R2: 29.565995 | S2: 28.552 | T2: 174840 | U2: WIN | V2: 28.857 | W2: 0 | X2: 53 | Y2: trailing_stop
A3: T00002 | B3: NQ | C3: indices | D3: short | E3: H&S | F3: 1H | G3: B | H3: APPROVED | I3: 8 | J3: 2026-01-09 06:15:00 | K3: 2026-01-09 19:35:00 | L3: 21790.75 | M3: 21807.781 | N3: 21420.799 | O3: 21341.378 | P3: 18 | Q3: 0.01215614 | R3: 22.195438 | S3: 22.246 | T3: 136359 | U3: WIN | V3: 23.058 | W3: 0 | X3: 53 | Y3: trailing_stop
A4: T00004 | B4: USDJPY | C4: forex | D4: short | E4: H&S | F4: 1H | G4: B | H4: APPROVED | I4: 8 | J4: 2026-01-09 06:15:00 | K4: 2026-01-09 20:40:00 | L4: 153.59 | M4: 153.67797 | N4: 151.54681 | O4: 151.1477 | P4: 100 | Q4: 0.012026138 | R4: 25.115046 | S4: 23.434 | T4: 133870.98 | U4: WIN | V4: 24.159 | W4: 0 | X4: 57 | Y4: trailing_stop
A5: T00003 | B5: RTY | C5: indices | D5: short | E5: H&S | F5: 1H | G5: B | H5: APPROVED | I5: 8 | J5: 2026-01-09 06:15:00 | K5: 2026-01-09 20:45:00 | L5: 2334.3 | M5: 2336.0991 | N5: 2290.6787 | O5: 2281.3907 | P5: 67 | Q5: 0.0123681 | R5: 24.719558 | S5: 24.574 | T5: 147971 | U5: WIN | V5: 25.481 | W5: 0 | X5: 58 | Y5: trailing_stop
A6: T00005 | B6: RTY | C6: indices | D6: long | E6: DB | F6: 1H | G6: B | H6: ELITE | I6: 9 | J6: 2026-01-14 11:45:00 | K6: 2026-01-14 19:05:00 | L6: 2233.6 | M6: 2231.4427 | N6: 2279.7012 | O6: 2281.3907 | P6: 200 | Q6: 0.019929333 | R6: 21.9982 | S6: 15.483 | T6: 333600 | U6: WIN | V6: 15.527 | W6: 0 | X6: 29 | Y6: early_exit_counter_pattern
A7: T00006 | B7: EURUSD | C7: forex | D7: long | E7: DB | F7: 1H | G7: B | H7: APPROVED | I7: 8 | J7: 2026-01-14 11:45:00 | K7: 2026-01-14 19:05:00 | L7: 1.0646 | M7: 1.0639575 | N7: 1.0785507 | O7: 1.0789495 | P7: 100 | Q7: 0.0060898052 | R7: 23.49999 | S7: 16.25 | T7: 104050 | U7: WIN | V7: 16.374 | W7: 0 | X7: 29 | Y7: early_exit_counter_pattern
A8: T00007 | B8: GBPUSD | C8: forex | D8: long | E8: DB | F8: 1H | G8: B | H8: APPROVED | I8: 8 | J8: 2026-01-14 11:45:00 | K8: 2026-01-14 19:05:00 | L8: 1.24615 | M8: 1.2453794 | N8: 1.2617948 | O8: 1.2629469 | P8: 100 | Q8: 0.0070156826 | R8: 22.556696 | S8: 15.495 | T8: 119050 | U8: WIN | V8: 15.6 | W8: 0 | X8: 29 | Y8: early_exit_counter_pattern
A9: T00008 | B9: GC | C9: commodities | D9: long | E9: DB | F9: 1H | G9: B | H9: ELITE | I9: 9 | J9: 2026-01-14 11:45:00 | K9: 2026-01-14 22:35:00 | L9: 2565.8 | M9: 2562.915 | N9: 2625.8297 | O9: 2634.5766 | P9: 65 | Q9: 0.016731317 | R9: 21.683885 | S9: 16.36 | T9: 306670 | U9: WIN | V9: 20.304 | W9: 0 | X9: 43 | Y9: trailing_stop
A10: T00009 | B10: EURUSD | C10: forex | D10: long | E10: DB | F10: 1H | G10: B | H10: APPROVED | I10: 7 | J10: 2026-01-15 17:15:00 | K10: 2026-01-16 04:05:00 | L10: 1.06481 | M10: 1.0641836 | N10: 1.0785507 | O10: 1.0787911 | P10: 100 | Q10: 0.0033396986 | R10: 23.627251 | S10: 17.545 | T10: 109550 | U10: WIN | V10: 19.103 | W10: 0 | X10: 43 | Y10: early_exit_counter_pattern
A11: T00010 | B11: GBPUSD | C11: forex | D11: short | E11: DT | F11: 1H | G11: B | H11: ELITE | I11: 9 | J11: 2026-01-19 06:15:00 | K11: 2026-01-19 10:05:00 | L11: 1.2766 | M11: 1.2773306 | N11: 1.2599115 | O11: 1.2578673 | P11: 100 | Q11: 0.0035242105 | R11: 25.469214 | S11: 9.239 | T11: 67150 | U11: WIN | V11: 9.337 | W11: 0 | X11: 15 | Y11: early_exit_counter_pattern
A12: T00011 | B12: GC | C12: commodities | D12: short | E12: DT | F12: 1H | G12: B | H12: ELITE | I12: 9 | J12: 2026-01-19 06:15:00 | K12: 2026-01-19 16:25:00 | L12: 2673.3 | M12: 2675.901 | N12: 2615.2896 | O12: 2606.0073 | P12: 163 | Q12: 0.019927121 | R12: 23.384206 | S12: 21.915 | T12: 928774 | U12: WIN | V12: 21.991 | W12: 0 | X12: 40 | Y12: end_of_backtest
A13: T00012 | B13: NQ | C13: indices | D13: short | E13: DT | F13: 1H | G13: B | H13: ELITE | I13: 9 | J13: 2026-01-19 06:15:00 | K13: 2026-01-19 16:25:00 | L13: 21655.75 | M13: 21672.31 | N13: 21261.555 | O13: 21208.655 | P13: 125 | Q13: 0.019993664 | R13: 24.165035 | S13: 23.536 | T13: 974125 | U13: WIN | V13: 23.575 | W13: 0 | X13: 40 | Y13: end_of_backtest
A14: T00013 | B14: RTY | C14: indices | D14: short | E14: DT | F14: 1H | G14: B | H14: ELITE | I14: 9 | J14: 2026-01-19 06:15:00 | K14: 2026-01-19 16:25:00 | L14: 2318.3 | M14: 2319.8158 | N14: 2273.2475 | O14: 2272.523 | P14: 183 | Q14: 0.0065536431 | R14: 32.269391 | S14: 29.961 | T14: 415174 | U14: WIN | V14: 30.515 | W14: 0 | X14: 40 | Y14: end_of_backtest

Sheet Research
A1: Trade ID | B1: Symbol | C1: Setup | D1: Why it was taken | E1: Plan | F1: Flagged at entry | G1: Realised R | H1: Exit reason
A2: T00001 | B2: GC | C2: GC SHORT · Head & Shoulders on 1H · APPROVED 7/10 | D2: Screen 1 has no directional bias, so this is traded on the formation alone rather than as a trend continuation (Ch IX). A Head & Shoulders completed on the 1H over 34 bars (three pushes higher, the middle one highest, every one of them sold into), grading textbook on 5 of 5 preferred filters (Ch XI pattern quality 2/2). The 15M closed at 2,692.26, 0.05 ATR through the neckline at 2,692.38 on 1.01x average volume (no surge), then price returned to the level and was rejected by a strong wick. The fill was taken on that rejection, which is the Method B fill the firm defaults to. The measured move projects 2,634.88, worth 29.57R against the stop at 2,695.54; the firm's floor is 2:1 (Ch VIII-A). | E2: PLAN: 30 contracts @ 2,693.50, SL 2,695.54, TP1 2,634.88 — 1.21% of account (6,074) at risk for 29.57R | F2: breakout volume 1.01x is below the Ch V-A 1.5x surge threshold; no independent S/R backs the entry or the target (Ch XI); Appendix A [P] missed — Is breakout volume > 1.5x the 20-period average? (1.01x average) | G2: 28.552 | H2: trailing_stop
A3: T00002 | B3: NQ | C3: NQ SHORT · Head & Shoulders on 1H · APPROVED 8/10 | D3: Screen 1 has no directional bias, so this is traded on the formation alone rather than as a trend continuation (Ch IX). A Head & Shoulders completed on the 1H over 36 bars (three pushes higher, the middle one highest, every one of them sold into), grading textbook on 5 of 5 preferred filters (Ch XI pattern quality 2/2). The 15M closed at 21,735.40, 3.87 ATR through the neckline at 21,796.89 on 2.14x the 20-bar average volume, then price returned to the level and was rejected by a strong wick. The fill was taken on that rejection, which is the Method B fill the firm defaults to. The measured move projects 21,420.80, worth 22.20R against the stop at 21,807.78; the firm's floor is 2:1 (Ch VIII-A). | E3: PLAN: 18 contracts @ 21,790.75, SL 21,807.78, TP1 21,420.80 — 1.22% of account (6,078) at risk for 22.20R | F3: no independent S/R backs the entry or the target (Ch XI) | G3: 22.246 | H3: trailing_stop
A4: T00004 | B4: USDJPY | C4: USDJPY SHORT · Head & Shoulders on 1H · APPROVED 8/10 | D4: Screen 1 has no directional bias, so this is traded on the formation alone rather than as a trend continuation (Ch IX). A Head & Shoulders completed on the 1H over 36 bars (three pushes higher, the middle one highest, every one of them sold into), grading textbook on 5 of 5 preferred filters (Ch XI pattern quality 2/2). The 15M closed at 153.317, 3.66 ATR through the neckline at 153.628 on 2.72x the 20-bar average volume, then price returned to the level and was rejected by a strong wick. The fill was taken on that rejection, which is the Method B fill the firm defaults to. The measured move projects 151.547, worth 25.12R against the stop at 153.678; the firm's floor is 2:1 (Ch VIII-A). | E4: PLAN: 100 lots @ 153.590, SL 153.678, TP1 151.547 — 1.20% of account (6,013) at risk for 25.12R | F4: no independent S/R backs the entry or the target (Ch XI) | G4: 23.434 | H4: trailing_stop
A5: T00003 | B5: RTY | C5: RTY SHORT · Head & Shoulders on 1H · APPROVED 8/10 | D5: Screen 1 has no directional bias, so this is traded on the formation alone rather than as a trend continuation (Ch IX). A Head & Shoulders completed on the 1H over 36 bars (three pushes higher, the middle one highest, every one of them sold into), grading textbook on 5 of 5 preferred filters (Ch XI pattern quality 2/2). The 15M closed at 2,327.31, 4.38 ATR through the neckline at 2,335.55 on 2.11x the 20-bar average volume, then price returned to the level and was rejected by a strong wick. The fill was taken on that rejection, which is the Method B fill the firm defaults to. The measured move projects 2,290.68, worth 24.72R against the stop at 2,336.10; the firm's floor is 2:1 (Ch VIII-A). | E5: PLAN: 67 contracts @ 2,334.30, SL 2,336.10, TP1 2,290.68 — 1.24% of account (6,184) at risk for 24.72R | F5: no independent S/R backs the entry or the target (Ch XI) | G5: 24.574 | H5: trailing_stop
A6: T00005 | B6: RTY | C6: RTY LONG · Double Bottom on 1H · ELITE 9/10 | D6: Screen 1 has no directional bias, so this is traded on the formation alone rather than as a trend continuation (Ch IX). A Double Bottom completed on the 1H over 19 bars (the same floor defended twice, the second attempt holding where the first did), grading textbook on 3 of 3 preferred filters (Ch XI pattern quality 2/2). The 15M closed at 2,234.39, 0.28 ATR through the confirmation line at 2,233.86 on 2.94x the 20-bar average volume, then price returned to the level and was rejected by a pin bar. The fill was taken on that rejection, which is the Method B fill the firm defaults to. The measured move projects 2,279.70, worth 22.00R against the stop at 2,231.44; the firm's floor is 2:1 (Ch VIII-A). | E6: PLAN: 200 contracts @ 2,233.60, SL 2,231.44, TP1 2,279.70 — 1.99% of account (21,784) at risk for 22.00R | F6: nothing flagged | G6: 15.483 | H6: early_exit_counter_pattern
A7: T00006 | B7: EURUSD | C7: EURUSD LONG · Double Bottom on 1H · APPROVED 8/10 | D7: Screen 1 has no directional bias, so this is traded on the formation alone rather than as a trend continuation (Ch IX). A Double Bottom completed on the 1H over 19 bars (the same floor defended twice, the second attempt holding where the first did), grading textbook on 3 of 3 preferred filters (Ch XI pattern quality 2/2). The 15M closed at 1.06455, 0.07 ATR through the confirmation line at 1.06451 on 2.66x the 20-bar average volume, then price returned to the level and was rejected by a pin bar. The fill was taken on that rejection, which is the Method B fill the firm defaults to. The measured move projects 1.07855, worth 23.50R against the stop at 1.06396; the firm's floor is 2:1 (Ch VIII-A). | E7: PLAN: 100 lots @ 1.06460, SL 1.06396, TP1 1.07855 — 0.61% of account (6,656) at risk for 23.50R | F7: no independent S/R backs the entry or the target (Ch XI) | G7: 16.25 | H7: early_exit_counter_pattern
A8: T00007 | B8: GBPUSD | C8: GBPUSD LONG · Double Bottom on 1H · APPROVED 8/10 | D8: Screen 1 has no directional bias, so this is traded on the formation alone rather than as a trend continuation (Ch IX). A Double Bottom completed on the 1H over 19 bars (the same floor defended twice, the second attempt holding where the first did), grading textbook on 3 of 3 preferred filters (Ch XI pattern quality 2/2). The 15M closed at 1.24587, 0.20 ATR through the confirmation line at 1.24574 on 2.79x the 20-bar average volume, then price returned to the level and was rejected by a strong wick. The fill was taken on that rejection, which is the Method B fill the firm defaults to. The measured move projects 1.26179, worth 22.56R against the stop at 1.24538; the firm's floor is 2:1 (Ch VIII-A). | E8: PLAN: 100 lots @ 1.24615, SL 1.24538, TP1 1.26179 — 0.70% of account (7,668) at risk for 22.56R | F8: no independent S/R backs the entry or the target (Ch XI) | G8: 15.495 | H8: early_exit_counter_pattern
A9: T00008 | B9: GC | C9: GC LONG · Double Bottom on 1H · ELITE 9/10 | D9: Screen 1 has no directional bias, so this is traded on the formation alone rather than as a trend continuation (Ch IX). A Double Bottom completed on the 1H over 19 bars (the same floor defended twice, the second attempt holding where the first did), grading textbook on 3 of 3 preferred filters (Ch XI pattern quality 2/2). The 15M closed at 2,566.78, 0.11 ATR through the confirmation line at 2,566.52 on 2.59x the 20-bar average volume, then price returned to the level and was rejected by a strong wick. The fill was taken on that rejection, which is the Method B fill the firm defaults to. The measured move projects 2,625.83, worth 21.68R against the stop at 2,562.91; the firm's floor is 2:1 (Ch VIII-A). | E9: PLAN: 65 contracts @ 2,565.80, SL 2,562.91, TP1 2,625.83 — 1.67% of account (18,288) at risk for 21.68R | F9: nothing flagged | G9: 16.36 | H9: trailing_stop
A10: T00009 | B10: EURUSD | C10: EURUSD LONG · Double Bottom on 1H · APPROVED 7/10 | D10: Screen 1 has no directional bias, so this is traded on the formation alone rather than as a trend continuation (Ch IX). A Double Bottom completed on the 1H over 19 bars (the same floor defended twice, the second attempt holding where the first did), grading textbook on 3 of 3 preferred filters (Ch XI pattern quality 2/2). The 15M closed at 1.06469, 0.48 ATR through the confirmation line at 1.06451 on 1.10x average volume (no surge), then price returned to the level and was rejected by a engulfing. The fill was taken on that rejection, which is the Method B fill the firm defaults to. The measured move projects 1.07855, worth 23.63R against the stop at 1.06418; the firm's floor is 2:1 (Ch VIII-A). | E10: PLAN: 100 lots @ 1.06481, SL 1.06418, TP1 1.07855 — 0.33% of account (6,534) at risk for 23.63R | F10: breakout volume 1.10x is below the Ch V-A 1.5x surge threshold; 1 opposing level(s) between entry and TP1 (nearest 1.06834); Appendix A [P] missed — Is breakout volume > 1.5x the 20-period average? (1.10x average); Appendix A [P] missed — Is path to TP1 clear of major S/R obstacles? (1 opposing level(s) between entry and TP1 (nearest 1.06834)) | G10: 17.545 | H10: early_exit_counter_pattern
A11: T00010 | B11: GBPUSD | C11: GBPUSD SHORT · Double Top on 1H · ELITE 9/10 | D11: Screen 1 has no directional bias, so this is traded on the formation alone rather than as a trend continuation (Ch IX). A Double Top completed on the 1H over 19 bars (the same ceiling rejected twice, the second attempt failing where the first did), grading textbook on 3 of 3 preferred filters (Ch XI pattern quality 2/2). The 15M closed at 1.27579, 0.98 ATR through the confirmation line at 1.27648 on 2.37x the 20-bar average volume, then price returned to the level and was rejected by a pin bar. The fill was taken on that rejection, which is the Method B fill the firm defaults to. The measured move projects 1.25991, worth 25.47R against the stop at 1.27733; the firm's floor is 2:1 (Ch VIII-A). | E11: PLAN: 100 lots @ 1.27660, SL 1.27733, TP1 1.25991 — 0.35% of account (7,281) at risk for 25.47R | F11: 1 opposing level(s) between entry and TP1 (nearest 1.27211); Appendix A [P] missed — Is path to TP1 clear of major S/R obstacles? (1 opposing level(s) between entry and TP1 (nearest 1.27211)) | G11: 9.239 | H11: early_exit_counter_pattern
A12: T00011 | B12: GC | C12: GC SHORT · Double Top on 1H · ELITE 9/10 | D12: Screen 1 has no directional bias, so this is traded on the formation alone rather than as a trend continuation (Ch IX). A Double Top completed on the 1H over 18 bars (the same ceiling rejected twice, the second attempt failing where the first did), grading textbook on 3 of 3 preferred filters (Ch XI pattern quality 2/2). The 15M closed at 2,673.72, 0.09 ATR through the confirmation line at 2,673.94 on 3.27x the 20-bar average volume, then price returned to the level and was rejected by a pin bar. The fill was taken on that rejection, which is the Method B fill the firm defaults to. The measured move projects 2,615.29, worth 23.38R against the stop at 2,675.90; the firm's floor is 2:1 (Ch VIII-A). | E12: PLAN: 163 contracts @ 2,673.30, SL 2,675.90, TP1 2,615.29 — 1.99% of account (41,169) at risk for 23.38R | F12: 1 opposing level(s) between entry and TP1 (nearest 2657.91886); Appendix A [P] missed — Is path to TP1 clear of major S/R obstacles? (1 opposing level(s) between entry and TP1 (nearest 2657.91886)) | G12: 21.915 | H12: end_of_backtest
A13: T00012 | B13: NQ | C13: NQ SHORT · Double Top on 1H · ELITE 9/10 | D13: Screen 1 has no directional bias, so this is traded on the formation alone rather than as a trend continuation (Ch IX). A Double Top completed on the 1H over 20 bars (the same ceiling rejected twice, the second attempt failing where the first did), grading textbook on 3 of 3 preferred filters (Ch XI pattern quality 2/2). The 15M closed at 21,634.81, 0.94 ATR through the confirmation line at 21,649.75 on 2.84x the 20-bar average volume, then price returned to the level and was rejected by a strong wick. The fill was taken on that rejection, which is the Method B fill the firm defaults to. The measured move projects 21,261.55, worth 24.17R against the stop at 21,672.31; the firm's floor is 2:1 (Ch VIII-A). | E13: PLAN: 125 contracts @ 21,655.75, SL 21,672.31, TP1 21,261.55 — 2.00% of account (41,306) at risk for 24.17R | F13: 1 opposing level(s) between entry and TP1 (nearest 21552.27413); Appendix A [P] missed — Is path to TP1 clear of major S/R obstacles? (1 opposing level(s) between entry and TP1 (nearest 21552.27413)) | G13: 23.536 | H13: end_of_backtest
A14: T00013 | B14: RTY | C14: RTY SHORT · Double Top on 1H · ELITE 9/10 | D14: Screen 1 has no directional bias, so this is traded on the formation alone rather than as a trend continuation (Ch IX). A Double Top completed on the 1H over 20 bars (the same ceiling rejected twice, the second attempt failing where the first did), grading textbook on 3 of 3 preferred filters (Ch XI pattern quality 2/2). The 15M closed at 2,318.66, 0.24 ATR through the confirmation line at 2,319.10 on 2.41x the 20-bar average volume, then price returned to the level and was rejected by a strong wick. The fill was taken on that rejection, which is the Method B fill the firm defaults to. The measured move projects 2,273.25, worth 32.27R against the stop at 2,319.82; the firm's floor is 2:1 (Ch VIII-A). | E14: PLAN: 183 contracts @ 2,318.30, SL 2,319.82, TP1 2,273.25 — 0.66% of account (13,540) at risk for 32.27R | F14: 1 opposing level(s) between entry and TP1 (nearest 2305.66943); Appendix A [P] missed — Is path to TP1 clear of major S/R obstacles? (1 opposing level(s) between entry and TP1 (nearest 2305.66943)) | G14: 29.961 | H14: end_of_backtest

Sheet Summary
A1: TITAN MARKETS LLC
A2: Summary
A3: Every figure is a formula over the Trades sheet.
A5: SYNTHETIC DATA — these numbers describe a generated price path, not market performance. Not a track record.
A9: Metric | B9: Value | C9: Note
A10: Trades | B10: =COUNTA(Trades!$B$2:$B$14) | C10: closed positions
A11: Wins | B11: =COUNTIF(Trades!$U$2:$U$14,"WIN")
A12: Losses | B12: =COUNTIF(Trades!$U$2:$U$14,"LOSS")
A13: Breakeven | B13: =COUNTIF(Trades!$U$2:$U$14,"BE")
A14: Win rate | B14: =IFERROR(B11/B10,0) | C14: Ch XIII-B target 50-60%
A15: Gross profit | B15: =SUMIF(Trades!$T$2:$T$14,">0")
A16: Gross loss | B16: =-SUMIF(Trades!$T$2:$T$14,"<0")
A17: Net P&L | B17: =SUM(Trades!$T$2:$T$14)
A18: Profit factor | B18: =IFERROR(B15/B16,"n/a") | C18: Ch XIII-B target > 1.5
A19: Expectancy per trade | B19: =IFERROR(B17/B10,0) | C19: must be positive
A20: Average R | B20: =IFERROR(AVERAGE(Trades!$S$2:$S$14),0) | C20: Ch XIII-B target > 2.0R
A21: Best R | B21: =IFERROR(MAX(Trades!$S$2:$S$14),0)
A22: Worst R | B22: =IFERROR(MIN(Trades!$S$2:$S$14),0)
A23: Starting balance | B23: 500000 | C23: input
A24: Ending balance | B24: =B23+B17
A25: Return | B25: =IFERROR(B17/B23,0)
A26: Max drawdown | B26: 0.20962 | C26: from Equity Curve high-water mark (RMG s.05 basis)
A27: Trades per week | B27: 6.25 | C27: Ch XIII-B target 3-8

Sheet By Instrument
A1: Symbol | B1: Asset class | C1: Screens (Ch IX) | D1: Trades | E1: Wins | F1: Win rate | G1: Avg R | H1: P&L | I1: Bars
A2: GC | B2: commodities | C2: 1D/1W > 4H/1H > 15M/5M | D2: =COUNTIF(Trades!$B$2:$B$14,A2) | E2: =COUNTIFS(Trades!$B$2:$B$14,A2,Trades!$U$2:$U$14,"WIN") | F2: =IFERROR(E2/D2,0) | G2: =IFERROR(AVERAGEIF(Trades!$B$2:$B$14,A2,Trades!$S$2:$S$14),0) | H2: =SUMIF(Trades!$B$2:$B$14,A2,Trades!$T$2:$T$14) | I2: 4230
A3: EURUSD | B3: forex | C3: 1D/1W > 4H/1H > 15M/5M | D3: =COUNTIF(Trades!$B$2:$B$14,A3) | E3: =COUNTIFS(Trades!$B$2:$B$14,A3,Trades!$U$2:$U$14,"WIN") | F3: =IFERROR(E3/D3,0) | G3: =IFERROR(AVERAGEIF(Trades!$B$2:$B$14,A3,Trades!$S$2:$S$14),0) | H3: =SUMIF(Trades!$B$2:$B$14,A3,Trades!$T$2:$T$14) | I3: 4230
A4: GBPUSD | B4: forex | C4: 1D/1W > 4H/1H > 15M/5M | D4: =COUNTIF(Trades!$B$2:$B$14,A4) | E4: =COUNTIFS(Trades!$B$2:$B$14,A4,Trades!$U$2:$U$14,"WIN") | F4: =IFERROR(E4/D4,0) | G4: =IFERROR(AVERAGEIF(Trades!$B$2:$B$14,A4,Trades!$S$2:$S$14),0) | H4: =SUMIF(Trades!$B$2:$B$14,A4,Trades!$T$2:$T$14) | I4: 4230
A5: USDJPY | B5: forex | C5: 1D/1W > 4H/1H > 15M/5M | D5: =COUNTIF(Trades!$B$2:$B$14,A5) | E5: =COUNTIFS(Trades!$B$2:$B$14,A5,Trades!$U$2:$U$14,"WIN") | F5: =IFERROR(E5/D5,0) | G5: =IFERROR(AVERAGEIF(Trades!$B$2:$B$14,A5,Trades!$S$2:$S$14),0) | H5: =SUMIF(Trades!$B$2:$B$14,A5,Trades!$T$2:$T$14) | I5: 4230
A6: CL | B6: commodities | C6: 1D/1W > 4H/1H > 15M/5M | D6: =COUNTIF(Trades!$B$2:$B$14,A6) | E6: =COUNTIFS(Trades!$B$2:$B$14,A6,Trades!$U$2:$U$14,"WIN") | F6: =IFERROR(E6/D6,0) | G6: =IFERROR(AVERAGEIF(Trades!$B$2:$B$14,A6,Trades!$S$2:$S$14),0) | H6: =SUMIF(Trades!$B$2:$B$14,A6,Trades!$T$2:$T$14) | I6: 4230
A7: NQ | B7: indices | C7: 1D > 4H/1H > 15M/5M | D7: =COUNTIF(Trades!$B$2:$B$14,A7) | E7: =COUNTIFS(Trades!$B$2:$B$14,A7,Trades!$U$2:$U$14,"WIN") | F7: =IFERROR(E7/D7,0) | G7: =IFERROR(AVERAGEIF(Trades!$B$2:$B$14,A7,Trades!$S$2:$S$14),0) | H7: =SUMIF(Trades!$B$2:$B$14,A7,Trades!$T$2:$T$14) | I7: 4230
A8: ES | B8: indices | C8: 1D > 4H/1H > 15M/5M | D8: =COUNTIF(Trades!$B$2:$B$14,A8) | E8: =COUNTIFS(Trades!$B$2:$B$14,A8,Trades!$U$2:$U$14,"WIN") | F8: =IFERROR(E8/D8,0) | G8: =IFERROR(AVERAGEIF(Trades!$B$2:$B$14,A8,Trades!$S$2:$S$14),0) | H8: =SUMIF(Trades!$B$2:$B$14,A8,Trades!$T$2:$T$14) | I8: 4230
A9: RTY | B9: indices | C9: 1D > 4H/1H > 15M/5M | D9: =COUNTIF(Trades!$B$2:$B$14,A9) | E9: =COUNTIFS(Trades!$B$2:$B$14,A9,Trades!$U$2:$U$14,"WIN") | F9: =IFERROR(E9/D9,0) | G9: =IFERROR(AVERAGEIF(Trades!$B$2:$B$14,A9,Trades!$S$2:$S$14),0) | H9: =SUMIF(Trades!$B$2:$B$14,A9,Trades!$T$2:$T$14) | I9: 4230
A10: TOTAL | D10: =SUM(D2:D9) | E10: =SUM(E2:E9) | F10: =IFERROR(E10/D10,0) | H10: =SUM(H2:H9) | I10: =SUM(I2:I9)

Sheet By Pattern
A1: Formation | B1: Trades | C1: Wins | D1: Win rate | E1: Avg R | F1: P&L
A2: DB | B2: =COUNTIF(Trades!$E$2:$E$14,A2) | C2: =COUNTIFS(Trades!$E$2:$E$14,A2,Trades!$U$2:$U$14,"WIN") | D2: =IFERROR(C2/B2,0) | E2: =IFERROR(AVERAGEIF(Trades!$E$2:$E$14,A2,Trades!$S$2:$S$14),0) | F2: =SUMIF(Trades!$E$2:$E$14,A2,Trades!$T$2:$T$14)
A3: DT | B3: =COUNTIF(Trades!$E$2:$E$14,A3) | C3: =COUNTIFS(Trades!$E$2:$E$14,A3,Trades!$U$2:$U$14,"WIN") | D3: =IFERROR(C3/B3,0) | E3: =IFERROR(AVERAGEIF(Trades!$E$2:$E$14,A3,Trades!$S$2:$S$14),0) | F3: =SUMIF(Trades!$E$2:$E$14,A3,Trades!$T$2:$T$14)
A4: H&S | B4: =COUNTIF(Trades!$E$2:$E$14,A4) | C4: =COUNTIFS(Trades!$E$2:$E$14,A4,Trades!$U$2:$U$14,"WIN") | D4: =IFERROR(C4/B4,0) | E4: =IFERROR(AVERAGEIF(Trades!$E$2:$E$14,A4,Trades!$S$2:$S$14),0) | F4: =SUMIF(Trades!$E$2:$E$14,A4,Trades!$T$2:$T$14)

Sheet By Grade
A1: Grade | B1: Trades | C1: Wins | D1: Win rate | E1: Avg R | F1: P&L
A2: APPROVED | B2: =COUNTIF(Trades!$H$2:$H$14,A2) | C2: =COUNTIFS(Trades!$H$2:$H$14,A2,Trades!$U$2:$U$14,"WIN") | D2: =IFERROR(C2/B2,0) | E2: =IFERROR(AVERAGEIF(Trades!$H$2:$H$14,A2,Trades!$S$2:$S$14),0) | F2: =SUMIF(Trades!$H$2:$H$14,A2,Trades!$T$2:$T$14)
A3: ELITE | B3: =COUNTIF(Trades!$H$2:$H$14,A3) | C3: =COUNTIFS(Trades!$H$2:$H$14,A3,Trades!$U$2:$U$14,"WIN") | D3: =IFERROR(C3/B3,0) | E3: =IFERROR(AVERAGEIF(Trades!$H$2:$H$14,A3,Trades!$S$2:$S$14),0) | F3: =SUMIF(Trades!$H$2:$H$14,A3,Trades!$T$2:$T$14)

Sheet Setup Funnel
A1: TITAN MARKETS LLC
A2: Setup funnel
A3: Ch XII-A4 requires refusals to be logged, not just fills.
A5: Outcome | B5: Count | C5: Share
A6: Executed | B6: 13 | C6: =IFERROR(B6/$B$11,0)
A7: Formation expired unbroken (Ch VI-B) | B7: 208 | C7: =IFERROR(B7/$B$11,0)
A8: Formation invalidated before entry (Ch V-B) | B8: 36 | C8: =IFERROR(B8/$B$11,0)
A9: Trade cadence cap (Ch XIII-B) | B9: 11 | C9: =IFERROR(B9/$B$11,0)
A10: Confluence score below 7/10 (Ch XI) | B10: 3 | C10: =IFERROR(B10/$B$11,0)
A11: TOTAL EVALUATED | B11: =SUM(B6:B10)

Sheet Risk & Compliance
A1: TITAN MARKETS LLC
A2: Risk and compliance
A3: Ch VIII-A hard limits and the RMG s.05 drawdown ladder.
A5: Measure | B5: Result | C5: Limit | D5: Verdict
A6: Peak aggregate open risk | B6: 0.049998638 | C6: 0.05 | D6: WITHIN
A7: Max drawdown (trailing) | B7: 0.20962 | C7: 0.12 | D7: BREACHED
A8: Bars with trading halted | B8: 428 | D8: 1.26% of run
A10: Account status timeline (RMG s.05)
A11: When | B11: From | C11: To | D11: Max DD | E11: Trading | F11: Breach
A12: 2026-01-09 16:15 | B12: ACTIVE | C12: PROBATION | D12: 0.11031 | E12: HALTED | F12: account drawdown 11.03% is in the probation band (RMG s.05)
A13: 2026-01-09 16:15 | B13: PROBATION | C13: SUSPENDED | D13: 0.17183 | E13: HALTED | F13: account drawdown 17.18% exceeds the 12% suspension trigger (RMG s.05)
A14: 2026-01-09 19:35 | B14: SUSPENDED | C14: PROBATION | D14: 0.10363 | E14: HALTED | F14: account drawdown 10.36% is in the probation band (RMG s.05)
A15: 2026-01-09 20:40 | B15: PROBATION | C15: ACTIVE | D15: 0.04341 | E15: permitted

Sheet Equity Curve
A1: Timestamp | B1: Equity | C1: High-water mark | D1: Drawdown
A2: 2026-01-05 02:55:00 | B2: 500000 | C2: =MAX($B$2:B2) | D2: =IFERROR((C2-B2)/C2,0)
A3: 2026-01-05 05:55:00 | B3: 500000 | C3: =MAX($B$2:B3) | D3: =IFERROR((C3-B3)/C3,0)
A4: 2026-01-05 08:55:00 | B4: 500000 | C4: =MAX($B$2:B4) | D4: =IFERROR((C4-B4)/C4,0)
A5: 2026-01-05 11:55:00 | B5: 500000 | C5: =MAX($B$2:B5) | D5: =IFERROR((C5-B5)/C5,0)
A6: 2026-01-05 14:55:00 | B6: 500000 | C6: =MAX($B$2:B6) | D6: =IFERROR((C6-B6)/C6,0)
A7: 2026-01-05 17:55:00 | B7: 500000 | C7: =MAX($B$2:B7) | D7: =IFERROR((C7-B7)/C7,0)
A8: 2026-01-05 20:55:00 | B8: 500000 | C8: =MAX($B$2:B8) | D8: =IFERROR((C8-B8)/C8,0)
A9: 2026-01-05 23:55:00 | B9: 500000 | C9: =MAX($B$2:B9) | D9: =IFERROR((C9-B9)/C9,0)
A10: 2026-01-06 02:55:00 | B10: 500000 | C10: =MAX($B$2:B10) | D10: =IFERROR((C10-B10)/C10,0)
A11: 2026-01-06 05:55:00 | B11: 500000 | C11: =MAX($B$2:B11) | D11: =IFERROR((C11-B11)/C11,0)
A12: 2026-01-06 08:55:00 | B12: 500000 | C12: =MAX($B$2:B12) | D12: =IFERROR((C12-B12)/C12,0)
A13: 2026-01-06 11:55:00 | B13: 500000 | C13: =MAX($B$2:B13) | D13: =IFERROR((C13-B13)/C13,0)
... A119: 2026-01-19 16:25:00 | B119: 4451184 | C119: =MAX($B$2:B119) | D119: =IFERROR((C119-B119)/C119,0)

Sheet Config
A1: Parameter | B1: Value | C1: Source
A2: Risk per trade — APPROVED | B2: 1.25% | C2: Ch XI / Ch VIII-A
A3: Risk per trade — ELITE | B3: 2.0% | C3: Ch XI
A4: Titan Entry cap | B4: 0.5% | C4: Ch XII-B
A5: Aggregate open risk cap | B5: 5.0% | C5: Ch VIII-A hard limit
A6: Minimum reward:risk | B6: 2.0:1 | C6: Ch VIII-A hard limit
A7: Correlated position cap | B7: 2 | C7: Ch VIII-A
A8: Daily loss limit | B8: 3.0% | C8: Ch VIII-A / Ch XII-A5
A9: Weekly loss limit | B9: 6.0% | C9: Ch VIII-A / Ch XII-A5
A10: Monthly DD trigger | B10: 10.0% | C10: Ch VIII-A
A11: Max DD ladder | B11: 8.0/10.0/12.0% | C11: RMG s.05
A12: Max DD basis | B12: trailing | C12: DERIVED
... A23: Entry screens | B23: 15M/5M | C23: Ch IX Screen 3
